{"chunk_definitions":[{"chunk_id":"cyj1okpp94zt9","chunk_label":"unnamed-chunk-1","document_id":"6834797C","expansion_state":0,"options":{"engine":"r","label":"unnamed-chunk-20"},"row":28,"row_count":1,"visible":true},{"chunk_id":"cmf0v5c8gm0gy","chunk_label":"unnamed-chunk-2","document_id":"6834797C","expansion_state":0,"options":{"engine":"r","label":"unnamed-chunk-21"},"row":47,"row_count":1,"visible":true},{"chunk_id":"c72gsweqqu323","chunk_label":"unnamed-chunk-3","document_id":"6834797C","expansion_state":0,"options":{"engine":"r","label":"unnamed-chunk-32"},"row":90,"row_count":1,"visible":true},{"chunk_id":"cwlw2brukjj7o","chunk_label":"unnamed-chunk-4","document_id":"6834797C","expansion_state":0,"options":{"engine":"r","label":"unnamed-chunk-33"},"row":96,"row_count":1,"visible":true},{"chunk_id":"ckw54umtscz3m","chunk_label":"unnamed-chunk-5","document_id":"6834797C","expansion_state":0,"options":{"engine":"r","label":"unnamed-chunk-34"},"row":185,"row_count":1,"visible":true},{"chunk_id":"c95da1oeqe9tf","chunk_label":"unnamed-chunk-6","document_id":"6834797C","expansion_state":0,"options":{"engine":"r","label":"unnamed-chunk-35"},"row":192,"row_count":1,"visible":true},{"chunk_id":"cbvwk3smhliwc","chunk_label":"unnamed-chunk-7","document_id":"6834797C","expansion_state":0,"options":{"engine":"r","label":"unnamed-chunk-36"},"row":199,"row_count":1,"visible":true}],"doc_write_time":1556763080}